pycrds/__init__.py
pycrds/datafile.py
pycrds/flags.py
pycrds/graphs.py
pycrds-0.0.1.dist-info/LICENSE
pycrds-0.0.1.dist-info/METADATA
pycrds-0.0.1.dist-info/WHEEL
pycrds-0.0.1.dist-info/top_level.txt
pycrds-0.0.1.dist-info/RECORD
