Metadata-Version: 2.1
Name: pycrds
Version: 0.0.1
Summary: A library to CRDS (cavity ring-down spectroscopy) data processing
Home-page: https://github.com/lapat-iag-usp/PyCRDS
Author: Marcia Marques
Author-email: marcia.marques@alumni.usp.br
Classifier: Development Status :: 2 - Pre-Alpha
Classifier: Intended Audience :: Science/Research
Classifier: Topic :: Scientific/Engineering :: Atmospheric Science
Classifier: License :: OSI Approved :: BSD License
Classifier: Programming Language :: Python :: 3.11
License-File: LICENSE
Requires-Dist: numpy>=1.26.4
Requires-Dist: pandas>=2.2.2
Requires-Dist: xarray>=2024.6.0
Requires-Dist: dask>=2024.5.2
Requires-Dist: dask-expr>=1.1.2
Requires-Dist: netCDF4>=1.6.5
